{
    "best_learning_rate": 0.00010000000000000003,
    "best_norm_strength": null,
    "results": [
        {
            "test_loss": 5.160332679748535,
            "test_MASE": 2.1153719425201416
        },
        {
            "test_loss": 5.283263683319092,
            "test_MASE": 2.1556410789489746
        },
        {
            "test_loss": 5.1531853675842285,
            "test_MASE": 2.1139488220214844
        },
        {
            "test_loss": 5.234306812286377,
            "test_MASE": 2.137974977493286
        },
        {
            "test_loss": 5.15309476852417,
            "test_MASE": 2.114060640335083
        },
        {
            "test_loss": 5.23792839050293,
            "test_MASE": 2.1392486095428467
        },
        {
            "test_loss": 5.184584140777588,
            "test_MASE": 2.121958017349243
        },
        {
            "test_loss": 5.144631385803223,
            "test_MASE": 2.11265230178833
        },
        {
            "test_loss": 5.142940998077393,
            "test_MASE": 2.113115072250366
        },
        {
            "test_loss": 5.245068073272705,
            "test_MASE": 2.141731023788452
        }
    ]
}